{
  "/_not-found/page": "app/_not-found/page.js",
  "/api/auth/debug-sms-config/route": "app/api/auth/debug-sms-config/route.js",
  "/api/auth/backup-pin/route": "app/api/auth/backup-pin/route.js",
  "/api/auth/debug-sms/route": "app/api/auth/debug-sms/route.js",
  "/api/auth/key-backup/route": "app/api/auth/key-backup/route.js",
  "/api/auth/salt/route": "app/api/auth/salt/route.js",
  "/api/auth/upload-avatar/route": "app/api/auth/upload-avatar/route.js",
  "/api/auth/session/route": "app/api/auth/session/route.js",
  "/api/auth/user/route": "app/api/auth/user/route.js",
  "/api/auth/send-sms/route": "app/api/auth/send-sms/route.js",
  "/api/chat/conversations/[id]/mark-read/route": "app/api/chat/conversations/[id]/mark-read/route.js",
  "/api/chat/conversations/[id]/participants/route": "app/api/chat/conversations/[id]/participants/route.js",
  "/api/auth/verify-sms/route": "app/api/auth/verify-sms/route.js",
  "/api/chat/messages/[id]/route": "app/api/chat/messages/[id]/route.js",
  "/api/chat/groups/route": "app/api/chat/groups/route.js",
  "/api/chat/conversations/route": "app/api/chat/conversations/route.js",
  "/api/chat/messages/route": "app/api/chat/messages/route.js",
  "/api/cleanup/empty-conversations/route": "app/api/cleanup/empty-conversations/route.js",
  "/api/cleanup/legacy-keys/route": "app/api/cleanup/legacy-keys/route.js",
  "/api/conversations/[id]/disappearing-messages/presets/route": "app/api/conversations/[id]/disappearing-messages/presets/route.js",
  "/api/cleanup/legacy-messages/route": "app/api/cleanup/legacy-messages/route.js",
  "/api/conversations/[id]/disappearing-messages/route": "app/api/conversations/[id]/disappearing-messages/route.js",
  "/api/crypto/public-keys/all/route": "app/api/crypto/public-keys/all/route.js",
  "/api/crypto/public-keys/route": "app/api/crypto/public-keys/route.js",
  "/api/events/route": "app/api/events/route.js",
  "/api/files/[fileId]/encrypted/route": "app/api/files/[fileId]/encrypted/route.js",
  "/api/files/[fileId]/route": "app/api/files/[fileId]/route.js",
  "/api/files/debug-upload/route": "app/api/files/debug-upload/route.js",
  "/api/files/message/[messageId]/route": "app/api/files/message/[messageId]/route.js",
  "/api/files/upload-url/route": "app/api/files/upload-url/route.js",
  "/api/files/upload/route": "app/api/files/upload/route.js",
  "/api/files/upload-complete/route": "app/api/files/upload-complete/route.js",
  "/api/keys/delete/route": "app/api/keys/delete/route.js",
  "/api/keys/reset/route": "app/api/keys/reset/route.js",
  "/api/plugins/execute/route": "app/api/plugins/execute/route.js",
  "/api/settings/disappearing-messages/route": "app/api/settings/disappearing-messages/route.js",
  "/api/sms/send-notification/route": "app/api/sms/send-notification/route.js",
  "/api/plugins/route": "app/api/plugins/route.js",
  "/api/user/nuclear-delete/route": "app/api/user/nuclear-delete/route.js",
  "/api/user/profile/route": "app/api/user/profile/route.js",
  "/api/users/search/route": "app/api/users/search/route.js",
  "/api/users/by-id/[identifier]/route": "app/api/users/by-id/[identifier]/route.js",
  "/api/user/profile/[userId]/route": "app/api/user/profile/[userId]/route.js",
  "/api/profile/update/route": "app/api/profile/update/route.js",
  "/api/webhooks/telnyx/sms/route": "app/api/webhooks/telnyx/sms/route.js",
  "/api/websocket/route": "app/api/websocket/route.js",
  "/api/conversations/archive/route": "app/api/conversations/archive/route.js",
  "/api/conversations/join/route": "app/api/conversations/join/route.js",
  "/api/conversations/load/route": "app/api/conversations/load/route.js",
  "/api/conversations/create/route": "app/api/conversations/create/route.js",
  "/api/conversations/unarchive/route": "app/api/conversations/unarchive/route.js",
  "/api/messages/load/route": "app/api/messages/load/route.js",
  "/api/conversations/delete/route": "app/api/conversations/delete/route.js",
  "/api/messages/send/route": "app/api/messages/send/route.js",
  "/api/typing/start/route": "app/api/typing/start/route.js",
  "/api/typing/stop/route": "app/api/typing/stop/route.js",
  "/api/webhooks/route": "app/api/webhooks/route.js",
  "/api/webhooks/[id]/route": "app/api/webhooks/[id]/route.js",
  "/about/page": "app/about/page.js",
  "/auth/page": "app/auth/page.js",
  "/contact/page": "app/contact/page.js",
  "/security/page": "app/security/page.js",
  "/page": "app/page.js",
  "/privacy/page": "app/privacy/page.js",
  "/premium/page": "app/premium/page.js",
  "/terms/page": "app/terms/page.js",
  "/chat/page": "app/chat/page.js",
  "/settings/page": "app/settings/page.js",
  "/warrant-canary/page": "app/warrant-canary/page.js"
}